secureshell/__init__.py
secureshell/audit.py
secureshell/config.py
secureshell/core.py
secureshell/gatekeeper.py
secureshell/models.py
secureshell/risk_engine.py
secureshell/sandbox.py
secureshell/templates.py
secureshell/integrations/__init__.py
secureshell/integrations/langchain.py
secureshell/integrations/langgraph.py
secureshell/integrations/mcp_server.py
secureshell/integrations/openai_tools.py
secureshell/providers/__init__.py
secureshell/providers/anthropic.py
secureshell/providers/base.py
secureshell/providers/deepseek.py
secureshell/providers/gemini.py
secureshell/providers/groq.py
secureshell/providers/llama_cpp.py
secureshell/providers/ollama.py
secureshell/providers/openai.py
secureshell-0.2.0.dist-info/METADATA
secureshell-0.2.0.dist-info/WHEEL
secureshell-0.2.0.dist-info/licenses/LICENSE
secureshell-0.2.0.dist-info/RECORD
