Metadata-Version: 2.4
Name: secureshell
Version: 0.2.0
Summary: A drop-in shell execution wrapper for LLM agents that prevents hallucinated/destructive commands.
Project-URL: Homepage, https://github.com/divagr18/secureshell
Project-URL: Repository, https://github.com/divagr18/secureshell.git
Project-URL: Bug Tracker, https://github.com/divagr18/secureshell/issues
Project-URL: Changelog, https://github.com/divagr18/secureshell/blob/main/CHANGELOG.md
Author-email: Divyansh Agrawal <keshav.r.1925@gmail.com>
License: MIT
License-File: LICENSE
Keywords: ai,anthropic,claude,command,langchain,llm,openai,security,shell
Requires-Python: >=3.9
Requires-Dist: aiofiles>=23.0.0
Requires-Dist: httpx>=0.25.0
Requires-Dist: pydantic-settings>=2.0.0
Requires-Dist: pydantic>=2.0.0
Requires-Dist: pyyaml>=6.0
Requires-Dist: structlog>=23.1.0
Requires-Dist: tenacity>=8.2.0
Requires-Dist: typing-extensions>=4.5.0
Provides-Extra: anthropic
Requires-Dist: anthropic>=0.18.0; extra == 'anthropic'
Provides-Extra: dev
Requires-Dist: black; extra == 'dev'
Requires-Dist: isort; extra == 'dev'
Requires-Dist: mypy; extra == 'dev'
Requires-Dist: ruff; extra == 'dev'
Provides-Extra: google
Requires-Dist: google-generativeai>=0.3.0; extra == 'google'
Provides-Extra: langchain
Requires-Dist: langchain-core>=0.1.0; extra == 'langchain'
Provides-Extra: mcp
Requires-Dist: mcp>=0.1.0; extra == 'mcp'
Provides-Extra: openai
Requires-Dist: openai>=1.0.0; extra == 'openai'
Provides-Extra: test
Requires-Dist: pytest-asyncio>=0.21.0; extra == 'test'
Requires-Dist: pytest-mock>=3.10.0; extra == 'test'
Requires-Dist: pytest>=7.0.0; extra == 'test'
